nqgcs/__init__.py
nqgcs/nqgcs.py
nqgcs-0.1.4.dist-info/LICENSE.md
nqgcs-0.1.4.dist-info/METADATA
nqgcs-0.1.4.dist-info/WHEEL
nqgcs-0.1.4.dist-info/top_level.txt
nqgcs-0.1.4.dist-info/RECORD
