Metadata-Version: 2.1
Name: nqgcs
Version: 0.1.4
Summary: Interface to Google Cloud Storage
Home-page: https://bitbucket.org/luca_de_alfaro/nqgcs
Author: Luca de Alfaro
Author-email: luca@dealfaro.com
Maintainer: Luca de Alfaro
Maintainer-email: luca@dealfaro.com
License: BSD
Platform: any
Classifier: Development Status :: 4 - Beta
Classifier: Intended Audience :: Developers
Classifier: License :: OSI Approved :: BSD License
Classifier: Operating System :: OS Independent
Classifier: Programming Language :: Python
Classifier: Programming Language :: Python :: Implementation :: CPython
Classifier: Topic :: Software Development :: Libraries :: Python Modules
Requires-Python: >=3.7
License-File: LICENSE.md
Requires-Dist: google-cloud-storage
Requires-Dist: google-auth
